across/__init__.py
across/client/__init__.py
across/client/_version.py
across/client/client.py
across/client/py.typed
across/client/apis/__init__.py
across/client/apis/filter.py
across/client/apis/instrument.py
across/client/apis/observation.py
across/client/apis/observatory.py
across/client/apis/schedule.py
across/client/apis/telescope.py
across/client/apis/tools.py
across/client/core/__init__.py
across/client/core/config.py
across_client-1.0.0.dist-info/licenses/LICENSE
across_client-1.0.0.dist-info/METADATA
across_client-1.0.0.dist-info/WHEEL
across_client-1.0.0.dist-info/top_level.txt
across_client-1.0.0.dist-info/RECORD
