Metadata-Version: 2.4
Name: across-client
Version: 1.0.0
Author-email: "Samuel D. Wyatt" <samuel.d.wyatt@nasa.gov>, "Jamie A. Kennea" <jak51@psu.edu>, Craig Pellegrino <craig.m.pellegrino@nasa.gov>
Maintainer-email: "Samuel D. Wyatt" <samuel.d.wyatt@nasa.gov>, "Jamie A. Kennea" <jak51@psu.edu>, Craig Pellegrino <craig.m.pellegrino@nasa.gov>
License:                                  Apache License
Project-URL: Source Code, https://github.com/NASA-ACROSS/across-client
Classifier: Development Status :: 4 - Beta
Classifier: Intended Audience :: Developers
Classifier: Intended Audience :: Science/Research
Classifier: Operating System :: OS Independent
Classifier: Programming Language :: Python
Requires-Python: >=3.10
License-File: LICENSE
Requires-Dist: across-tools
Requires-Dist: across-server-openapi-python
Provides-Extra: dev
Requires-Dist: jupyter; extra == "dev"
Requires-Dist: mypy; extra == "dev"
Requires-Dist: pre-commit; extra == "dev"
Requires-Dist: pytest; extra == "dev"
Requires-Dist: pytest-cov; extra == "dev"
Requires-Dist: ruff; extra == "dev"
Requires-Dist: sphinx-autoapi; extra == "dev"
Requires-Dist: nbsphinx; extra == "dev"
Requires-Dist: sphinx-copybutton; extra == "dev"
Requires-Dist: sphinx-rtd-theme; extra == "dev"
Requires-Dist: types-shapely; extra == "dev"
Dynamic: license-file
